README.md
setup.cfg
setup.py
result2/__init__.py
result2/result2.py
result2/test.py
result2.egg-info/PKG-INFO
result2.egg-info/SOURCES.txt
result2.egg-info/dependency_links.txt
result2.egg-info/top_level.txt
result2.egg-info/zip-safe